fabexp_helper/__init__.py
fabexp_helper/fabexp.py
fabexp_helper/modules/img/fabric_logo.png
fabexp_helper/modules/ipyCreate.py
fabexp_helper/modules/templates/accessing_ipv4_services_from_ipv6_nodes/accessing_ipv4_services_from_ipv6_nodes.ipynb
fabexp_helper/modules/templates/accessing_ipv4_services_from_ipv6_nodes/upload/nat64.sh
fabexp_helper/modules/templates/basic_gpu_devices/basic_gpu_devices.ipynb
fabexp_helper/modules/templates/basic_nvme_devices/basic_nvme_devices.ipynb
fabexp_helper/modules/templates/benchmarking_storage/benchmarking_storage.ipynb
fabexp_helper/modules/templates/create_l2network_basic/create_l2network_basic.ipynb
fabexp_helper/modules/templates/create_l2network_wide_area/create_l2network_wide_area.ipynb
fabexp_helper/modules/templates/create_l3network_fabnet_ipv4/create_l3network_fabnet_ipv4.ipynb
fabexp_helper/modules/templates/create_l3network_fabnet_ipv6/create_l3network_fabnet_ipv6.ipynb
fabexp_helper/modules/templates/create_slice/create_slice.ipynb
fabexp_helper/modules/templates/customizing_nodes/customizing_nodes.ipynb
fabexp_helper/modules/templates/delete_slice/delete_slice.ipynb
fabexp_helper/modules/templates/fablib_common/fablib_common.ipynb
fabexp_helper/modules/templates/fablib_common/fields.ipynb
fabexp_helper/modules/templates/fablib_common/filters.ipynb
fabexp_helper/modules/templates/fablib_common/list.ipynb
fabexp_helper/modules/templates/fablib_common/logging.ipynb
fabexp_helper/modules/templates/fablib_common/random_sites.ipynb
fabexp_helper/modules/templates/fablib_common/show.ipynb
fabexp_helper/modules/templates/fablib_common/table_styles.ipynb
fabexp_helper/modules/templates/facility_port/facility_port.ipynb
fabexp_helper/modules/templates/get_nodes/get_nodes.ipynb
fabexp_helper/modules/templates/hello_fabric/configure.ipynb
fabexp_helper/modules/templates/hello_fabric/hello_fabric.ipynb
fabexp_helper/modules/templates/hello_fabric/include/figs/FABRIC_ExampleFigs.pptx
fabexp_helper-0.0.5.dist-info/LICENSE
fabexp_helper-0.0.5.dist-info/WHEEL
fabexp_helper-0.0.5.dist-info/entry_points.txt
fabexp_helper-0.0.5.dist-info/METADATA
fabexp_helper-0.0.5.dist-info/RECORD
