Metadata-Version: 2.1
Name: fabexp-helper
Version: 0.0.5
Summary: A tool to help create and manage fabric experiments
Author: Devin Lane
Author-email: silvertenor@icloud.com
Requires-Python: >=3.9,<4.0
Classifier: Programming Language :: Python :: 3
Classifier: Programming Language :: Python :: 3.9
Classifier: Programming Language :: Python :: 3.10
Classifier: Programming Language :: Python :: 3.11
Requires-Dist: click (>=8.1.3,<9.0.0)
Requires-Dist: nbformat (>=5.7.3,<6.0.0)
